qseek.libs/libgomp-ba615989.so.1.0.0
qseek/utils.py
qseek/py.typed
qseek/search.py
qseek/server.py
qseek/octree.py
qseek/__init__.py
qseek/stats.py
qseek/testing.py
qseek/signals.py
qseek/console.py
qseek/test.py
qseek/distance_weights.py
qseek/images/images.py
qseek/images/__init__.py
qseek/images/seisbench.py
qseek/images/base.py
qseek/features/__init__.py
qseek/features/ground_motion.py
qseek/features/base.py
qseek/apps/qseek.py
qseek/apps/__init__.py
qseek/pre_processing/deep_denoiser.py
qseek/pre_processing/module.py
qseek/pre_processing/downsample.py
qseek/pre_processing/__init__.py
qseek/pre_processing/frequency_filters.py
qseek/pre_processing/base.py
qseek/corrections/corrections.py
qseek/corrections/simple.py
qseek/corrections/__init__.py
qseek/corrections/base.py
qseek/tracers/cake.py
qseek/tracers/__init__.py
qseek/tracers/tracers.py
qseek/tracers/constant_velocity.py
qseek/tracers/base.py
qseek/models/__init__.py
qseek/models/detection.py
qseek/models/station.py
qseek/models/location.py
qseek/models/detection_uncertainty.py
qseek/models/catalog.py
qseek/models/semblance.py
qseek/exporters/simple.py
qseek/exporters/velest.py
qseek/exporters/__init__.py
qseek/exporters/base.py
qseek/waveforms/squirrel.py
qseek/waveforms/__init__.py
qseek/waveforms/providers.py
qseek/waveforms/base.py
qseek/magnitudes/local_magnitude_model.py
qseek/magnitudes/local_magnitude.py
qseek/magnitudes/moment_magnitude.py
qseek/magnitudes/__init__.py
qseek/magnitudes/moment_magnitude_store.py
qseek/magnitudes/base.py
qseek/plot/utils.py
qseek/plot/manager.py
qseek/plot/octree.py
qseek/plot/__init__.py
qseek/plot/catalog.py
qseek/plot/base.py
qseek/ext/array_tools.cpython-311-x86_64-linux-musl.so
qseek/ext/array_tools.pyi
qseek/ext/array_tools.c
qseek-0.1.1.dist-info/entry_points.txt
qseek-0.1.1.dist-info/RECORD
qseek-0.1.1.dist-info/METADATA
qseek-0.1.1.dist-info/WHEEL
qseek-0.1.1.dist-info/top_level.txt
qseek-0.1.1.dist-info/LICENSE
