Metadata-Version: 2.1
Name: qseek
Version: 0.1.1
Summary: qseek - The earthquake detector.
Author-email: Marius Paul Isken <mi@gfz-potsdam.de>, Sebastian Heimann <heimann@uni-potsdam.de>, Marius Kriegerowski <mk@quakesaver.de>
Maintainer-email: Marius Paul Isken <mi@gfz-potsdam.de>, Sebastian Heimann <heimann@uni-potsdam.de>
License: GPLv3
Project-URL: Home, https://pyrocko.org
Project-URL: GitHub, https://github.com/pyrocko/qseek
Project-URL: Issues, https://github.com/pyrocko/qseek/issues
Keywords: earthquake,detection,localization,stacking-migration,beamforming
Classifier: Development Status :: 4 - Beta
Classifier: Intended Audience :: Science/Research
Classifier: Topic :: Scientific/Engineering
Classifier: Topic :: Scientific/Engineering :: Physics
Classifier: Topic :: Scientific/Engineering :: Information Analysis
Classifier: Operating System :: POSIX
Classifier: Operating System :: MacOS
Classifier: Typing :: Typed
Classifier: Programming Language :: Python :: 3 :: Only
Classifier: License :: OSI Approved :: GNU General Public License v3 or later (GPLv3+)
Requires-Python: <3.13,>=3.10
License-File: LICENSE
Requires-Dist: numpy<2,>=1.17.3
Requires-Dist: scipy>=1.8.0
Requires-Dist: pyrocko>=2022.06.10
Requires-Dist: seisbench>=0.5.0
Requires-Dist: pydantic>=2.5.0
Requires-Dist: aiohttp>=3.8
Requires-Dist: aiohttp_cors>=0.7.0
Requires-Dist: typing-extensions>=4.6
Requires-Dist: lru-dict>=1.3
Requires-Dist: rich>=13.4
Requires-Dist: nest_asyncio>=1.5
Requires-Dist: pyevtk>=1.6
Requires-Dist: psutil>=5.9
Requires-Dist: aiofiles>=23.0
Requires-Dist: typer>=0.12.3
Requires-Dist: scikit-fmm>=2024.05
Provides-Extra: dev
Requires-Dist: pre-commit>=3.4; extra == "dev"
Requires-Dist: ruff>=0.3.0; extra == "dev"
Requires-Dist: pytest>=7.4; extra == "dev"
Requires-Dist: pytest-asyncio>=0.21; extra == "dev"
Provides-Extra: docs
Requires-Dist: mkdocs-material>=9.5; extra == "docs"
Requires-Dist: mkdocstrings[python]>=0.25; extra == "docs"
Requires-Dist: griffe-pydantic>=1.1.0; extra == "docs"
Requires-Dist: markdown-exec>=1.9; extra == "docs"
Provides-Extra: completion
Requires-Dist: argcomplete>=3.2; extra == "completion"
